vlsi/and_gate_p.v
module full_adder(input a, b, cin, output S, Cout);
  assign S = a ^ b ^ cin;
  assign Cout = (a & b) | (b & cin) | (a & cin);
endmodule

vlsi/and_gate_assign_tb.v
module tb_top;
  reg a, b, c;
  wire s, c_out;
  
  full_adder fa(a, b, c, s, c_out);
  
  initial begin
    $dumpfile("full_adder.vcd");
    $dumpvars;
    $monitor("At time %0t: a=%b b=%b, cin=%b, sum=%b, carry=%b",$time, a,b,c,s,c_out);
    a = 0; b = 0; c = 0; #1;
    a = 0; b = 0; c = 1; #1;
    a = 0; b = 1; c = 0; #1;
    a = 0; b = 1; c = 1; #1;
    a = 1; b = 0; c = 0; #1;
    a = 1; b = 0; c = 1; #1;
    a = 1; b = 1; c = 0; #1;
    a = 1; b = 1; c = 1;
  end
endmodule

vlsi/full_adder.vcd
$date
	Fri Jul 04 00:20:30 2025
$end
$version
	Icarus Verilog
$end
$timescale
	1s
$end
$scope module tb_top $end
$var wire 1 ! s $end
$var wire 1 " c_out $end
$var reg 1 # a $end
$var reg 1 $ b $end
$var reg 1 % c $end
$scope module fa $end
$var wire 1 " Cout $end
$var wire 1 ! S $end
$var wire 1 # a $end
$var wire 1 $ b $end
$var wire 1 % cin $end
$upscope $end
$upscope $end
$enddefinitions $end
$comment Show the parameter values. $end
$dumpall
$end
#0
$dumpvars
0%
0$
0#
0"
0!
$end
#1
1!
1%
#2
0%
1$
#3
1"
0!
1%
#4
0"
1!
0%
0$
1#
#5
1"
0!
1%
#6
0%
1$
#7
1!
1%
